[{"_path":"/programs/professional-development","_dir":"programs","_draft":false,"_partial":false,"_locale":"","_empty":false,"title":"Professional Development Events","description":"IIREM organizes professional development events such as conferences, seminars, and panel discussions featuring industry experts, thought leaders, and prominent speakers. These events provide a platform for networking, knowledge sharing, and staying updated on the latest developments in the real estate sector.","cover":"/articles/configure-alpine.webp","layout":"article","_type":"markdown","_id":"content:programs:09.professional-development.md","_source":"content","_file":"programs/09.professional-development.md","_extension":"md"},{"_path":"/programs/international-study","_dir":"programs","_draft":false,"_partial":false,"_locale":"","_empty":false,"title":"International Study Programs","description":"IIREM facilitates international study programs that allow real estate professionals to explore global real estate markets, best practices, and cultural contexts. These programs offer valuable exposure to different real estate ecosystems, fostering cross-cultural understanding and international collaboration opportunities.","cover":"/articles/design-tokens.webp","layout":"article","_type":"markdown","_id":"content:programs:11.international-study.md","_source":"content","_file":"programs/11.international-study.md","_extension":"md"}]